ppip.pth
ppip/__init__.py
ppip/_post_install.py
ppip/backend.py
ppip/post.py
ppip/ppip.pth
ppip/pth.py
ppip/cli/__main__.py
ppip/cli/project.py
ppip/config/pyproject.toml
ppip/data/Brewfile
ppip/env/__init__.py
ppip/env/default.py
ppip/env/env.py
ppip/env/main.py
ppip/env/misc.py
ppip/env/osrelease.py
ppip/env/secrets.py
ppip/env/system.py
ppip/utils/__init__.py
ppip/utils/alias.py
ppip/utils/classes.py
ppip/utils/color.py
ppip/utils/color.pyi
ppip/utils/constants.py
ppip/utils/enums.py
ppip/utils/errors.py
ppip/utils/functions.py
ppip/utils/path.py
ppip/utils/path.pyi
ppip/utils/project.py
ppip/utils/repo.py
ppip/utils/start.py
ppip/utils/typings.py
ppip/utils/variables.py
bapy-2.0.5.dist-info/LICENSE
bapy-2.0.5.dist-info/METADATA
bapy-2.0.5.dist-info/WHEEL
bapy-2.0.5.dist-info/entry_points.txt
bapy-2.0.5.dist-info/top_level.txt
bapy-2.0.5.dist-info/RECORD
